help/__init__.py
rayvision_maya/__init__.py
rayvision_maya/analyze_maya.py
rayvision_maya/constants.py
rayvision_maya/temp.py
rayvision_maya/Analyze/__init__.py
rayvision_maya/Analyze/py26/Analyze.pyd
rayvision_maya/Analyze/py26/Analyze.so
rayvision_maya/Analyze/py26/__init__.py
rayvision_maya/Analyze/py27/Analyze.pyd
rayvision_maya/Analyze/py27/Analyze.so
rayvision_maya/Analyze/py27/__init__.py
rayvision_maya/Analyze/py310/Analyze.pyd
rayvision_maya/Analyze/py310/Analyze.so
rayvision_maya/Analyze/py310/__init__.py
rayvision_maya/Analyze/py311/Analyze.pyd
rayvision_maya/Analyze/py311/__init__.py
rayvision_maya/Analyze/py37/Analyze.pyd
rayvision_maya/Analyze/py37/Analyze.so
rayvision_maya/Analyze/py37/__init__.py
rayvision_maya/Analyze/py39/Analyze.pyd
rayvision_maya/Analyze/py39/Analyze.so
rayvision_maya/Analyze/py39/__init__.py
rayvision_maya/tests/__init__.py
rayvision_maya/tests/conftest.py
rayvision_maya/tests/test_analyze_maya.py
rayvision_maya-1.5.1.dist-info/METADATA
rayvision_maya-1.5.1.dist-info/WHEEL
rayvision_maya-1.5.1.dist-info/top_level.txt
rayvision_maya-1.5.1.dist-info/RECORD
